tf2cv/__init__.py
tf2cv/model_provider.py
tf2cv/models/__init__.py
tf2cv/models/airnet.py
tf2cv/models/airnext.py
tf2cv/models/alexnet.py
tf2cv/models/alphapose_coco.py
tf2cv/models/bagnet.py
tf2cv/models/bamresnet.py
tf2cv/models/bisenet.py
tf2cv/models/bninception.py
tf2cv/models/cbamresnet.py
tf2cv/models/centernet.py
tf2cv/models/cgnet.py
tf2cv/models/common.py
tf2cv/models/dabnet.py
tf2cv/models/danet.py
tf2cv/models/darknet.py
tf2cv/models/darknet53.py
tf2cv/models/deeplabv3.py
tf2cv/models/densenet.py
tf2cv/models/densenet_cifar.py
tf2cv/models/dicenet.py
tf2cv/models/diracnetv2.py
tf2cv/models/dla.py
tf2cv/models/dpn.py
tf2cv/models/drn.py
tf2cv/models/efficientnet.py
tf2cv/models/efficientnetedge.py
tf2cv/models/espnetv2.py
tf2cv/models/fastscnn.py
tf2cv/models/fastseresnet.py
tf2cv/models/fbnet.py
tf2cv/models/fcn8sd.py
tf2cv/models/fdmobilenet.py
tf2cv/models/fpenet.py
tf2cv/models/ghostnet.py
tf2cv/models/grmiposelite_coco.py
tf2cv/models/hardnet.py
tf2cv/models/hrnet.py
tf2cv/models/ibnbresnet.py
tf2cv/models/ibndensenet.py
tf2cv/models/ibnresnet.py
tf2cv/models/ibnresnext.py
tf2cv/models/ibppose_coco.py
tf2cv/models/icnet.py
tf2cv/models/igcv3.py
tf2cv/models/inceptionresnetv1.py
tf2cv/models/inceptionresnetv2.py
tf2cv/models/inceptionv3.py
tf2cv/models/inceptionv4.py
tf2cv/models/jasper.py
tf2cv/models/jasperdr.py
tf2cv/models/lednet.py
tf2cv/models/lffd.py
tf2cv/models/lwopenpose_cmupan.py
tf2cv/models/menet.py
tf2cv/models/mixnet.py
tf2cv/models/mnasnet.py
tf2cv/models/mobilenet.py
tf2cv/models/mobilenet_cub.py
tf2cv/models/mobilenetb.py
tf2cv/models/mobilenetv2.py
tf2cv/models/mobilenetv3.py
tf2cv/models/model_store.py
tf2cv/models/nasnet.py
tf2cv/models/nvpattexp.py
tf2cv/models/peleenet.py
tf2cv/models/pnasnet.py
tf2cv/models/polynet.py
tf2cv/models/preresnet.py
tf2cv/models/preresnet_cifar.py
tf2cv/models/proxylessnas.py
tf2cv/models/proxylessnas_cub.py
tf2cv/models/pspnet.py
tf2cv/models/pyramidnet.py
tf2cv/models/pyramidnet_cifar.py
tf2cv-0.0.18.dist-info/LICENSE.txt
tf2cv-0.0.18.dist-info/METADATA
tf2cv-0.0.18.dist-info/WHEEL
tf2cv-0.0.18.dist-info/top_level.txt
tf2cv-0.0.18.dist-info/RECORD
