Metadata-Version: 2.1
Name: tf2cv
Version: 0.0.18
Summary: Image classification models for TensorFlow 2.0
Home-page: https://github.com/osmr/imgclsmob
Author: Oleg Sémery
Author-email: osemery@gmail.com
License: MIT
Keywords: machine-learning deep-learning neuralnetwork image-classification tensorflow imagenet vgg resnet resnext senet densenet darknet squeezenet squeezenext shufflenet menet mobilenent igcv3 mnasnet
Platform: UNKNOWN
Classifier: Development Status :: 3 - Alpha
Classifier: Intended Audience :: Science/Research
Classifier: License :: OSI Approved :: MIT License
Classifier: Operating System :: OS Independent
Classifier: Programming Language :: Python
Classifier: Topic :: Scientific/Engineering :: Image Recognition
License-File: LICENSE.txt
Requires-Dist: numpy
Requires-Dist: requests
